{
  "kind": "collectionType",
  "collectionName": "prices",
  "info": {
    "singularName": "price",
    "pluralName": "prices",
    "displayName": "price",
    "description": ""
  },
  "options": {
    "draftAndPublish": true
  },
  "pluginOptions": {
    "i18n": {
      "localized": true
    }
  },
  "attributes": {
    "price": {
      "type": "string",
      "pluginOptions": {
        "i18n": {
          "localized": true
        }
      }
    },
    "features": {
      "type": "relation",
      "relation": "oneToMany",
      "target": "api::list.list"
    },
    "title": {
      "type": "string",
      "required": true,
      "pluginOptions": {
        "i18n": {
          "localized": true
        }
      }
    },
    "p1": {
      "pluginOptions": {
        "i18n": {
          "localized": true
        }
      },
      "type": "text"
    },
    "p2": {
      "pluginOptions": {
        "i18n": {
          "localized": true
        }
      },
      "type": "text"
    }
  }
}
